{
    "address1": "One John Deere Place",
    "city": "Moline",
    "state": "IL",
    "zip": "61265",
    "country": "United States",
    "phone": "309 765 8000",
    "website": "https://www.deere.com/en",
    "industry": "Farm & Heavy Construction Machinery",
    "industryKey": "farm-heavy-construction-machinery",
    "industryDisp": "Farm & Heavy Construction Machinery",
    "sector": "Industrials",
    "sectorKey": "industrials",
    "sectorDisp": "Industrials",
    "longBusinessSummary": "Deere & Company engages in the manufacture and distribution of various equipment worldwide. The company operates through four segments: Production and Precision Agriculture, Small Agriculture and Turf, Construction and Forestry, and Financial Services. The Production and Precision Agriculture segment provides large and mid-size tractors, combines, cotton pickers and strippers, sugarcane harvesters and loaders, soil preparation, tillage, seeding, and crop care equipment, as well as application equipment, including sprayers and nutrient management, soil preparation machinery for grain growers, and related attachments and service parts. The Small Agriculture and Turf segment offers rotary mowers, hay and forage equipment, forage harvesters, utility tractors, and related loaders and attachments; turf and utility equipment, including riding lawn, commercial mowing, and golf course equipment, and utility vehicles; and other outdoor power products, as well as implements for mowing, tilling, snow and debris handling, aerating, residential, commercial, golf, and sports turf care applications. The Construction and Forestry segment provides backhoe loaders, crawler dozers and loaders, four-wheel-drive loaders, track loaders, excavators, motor graders, articulated dump trucks, landscape and skid-steer loaders, scraper systems, milling machines, recyclers, slipform and asphalt pavers, surface miners, compactors, tandem, static rollers, mobile crushers and screens, mobile and stationary asphalt plants, log skidders and harvesters, log feller bunchers, and log loaders and forwarders; and road building and rehabilitation equipment. The Financial Services segment finances sales and leases agriculture and turf, and construction and forestry equipment. It also offers wholesale financing to dealers of the foregoing equipment; and extended equipment warranties, as well as finances retail revolving charge accounts. The company was founded in 1837 and is headquartered in Moline, Illinois.",
    "fullTimeEmployees": 75800,
    "companyOfficers": [
        {
            "maxAge": 1,
            "name": "Mr. John C. May II",
            "age": 55,
            "title": "Chairman, President & CEO",
            "yearBorn": 1969,
            "fiscalYear": 2024,
            "totalPay": 8611267,
            "exercisedValue": 0,
            "unexercisedValue": 9958258
        },
        {
            "maxAge": 1,
            "name": "Mr. Joshua A. Jepsen",
            "age": 46,
            "title": "Senior VP & CFO",
            "yearBorn": 1978,
            "fiscalYear": 2024,
            "totalPay": 2848784,
            "exercisedValue": 0,
            "unexercisedValue": 0
        },
        {
            "maxAge": 1,
            "name": "Mr. Rajesh  Kalathur",
            "age": 56,
            "title": "President of John Deere Financial & Chief Information Officer",
            "yearBorn": 1968,
            "fiscalYear": 2024,
            "totalPay": 2981116,
            "exercisedValue": 0,
            "unexercisedValue": 21736440
        },
        {
            "maxAge": 1,
            "name": "Mr. Ryan D. Campbell",
            "age": 49,
            "title": "President of Worldwide Construction, Forestry Equipment & Power Systems Division",
            "yearBorn": 1975,
            "fiscalYear": 2024,
            "totalPay": 2993001,
            "exercisedValue": 0,
            "unexercisedValue": 1848779
        },
        {
            "maxAge": 1,
            "name": "Mr. Cory J. Reed",
            "age": 53,
            "title": "President of Precision Ag for Americas & Aus and International President Sml Agri & Grn Space Equip",
            "yearBorn": 1971,
            "fiscalYear": 2024,
            "totalPay": 2935485,
            "exercisedValue": 3068281,
            "unexercisedValue": 6715494
        },
        {
            "maxAge": 1,
            "name": "Mr. Jahmy J. Hindman",
            "age": 48,
            "title": "Senior VP & CTO",
            "yearBorn": 1976,
            "fiscalYear": 2024,
            "exercisedValue": 0,
            "unexercisedValue": 0
        },
        {
            "maxAge": 1,
            "name": "Josh  Beal",
            "title": "Director of Investor Relations",
            "fiscalYear": 2024,
            "exercisedValue": 0,
            "unexercisedValue": 0
        },
        {
            "maxAge": 1,
            "name": "Ms. Renee A. Mailhot",
            "title": "VP & Chief Compliance Officer",
            "fiscalYear": 2024,
            "exercisedValue": 0,
            "unexercisedValue": 0
        },
        {
            "maxAge": 1,
            "name": "Ms. Kellye L. Walker J.D.",
            "age": 57,
            "title": "Senior VP, Chief Legal Officer and Global Law Services & Regulatory Affairs",
            "yearBorn": 1967,
            "fiscalYear": 2024,
            "exercisedValue": 0,
            "unexercisedValue": 0
        },
        {
            "maxAge": 1,
            "name": "Ms. Felecia J. Pryor J.D.",
            "age": 49,
            "title": "Senior VP & Chief People Officer",
            "yearBorn": 1975,
            "fiscalYear": 2024,
            "exercisedValue": 0,
            "unexercisedValue": 0
        }
    ],
    "auditRisk": 7,
    "boardRisk": 5,
    "compensationRisk": 9,
    "shareHolderRightsRisk": 7,
    "overallRisk": 7,
    "governanceEpochDate": 1761955200,
    "compensationAsOfEpochDate": 1735603200,
    "irWebsite": "http://phx.corporate-ir.net/phoenix.zhtml?c=83523&p=irol-stockquote",
    "executiveTeam": [],
    "maxAge": 86400,
    "priceHint": 2,
    "previousClose": 465.41,
    "open": 463.57,
    "dayLow": 458.72,
    "dayHigh": 464.54,
    "regularMarketPreviousClose": 465.41,
    "regularMarketOpen": 463.57,
    "regularMarketDayLow": 458.72,
    "regularMarketDayHigh": 464.54,
    "dividendRate": 6.48,
    "dividendYield": 1.4,
    "exDividendDate": 1759190400,
    "payoutRatio": 0.3305,
    "fiveYearAvgDividendYield": 1.21,
    "beta": 1.031,
    "trailingPE": 24.093424,
    "forwardPE": 20.822283,
    "volume": 870823,
    "regularMarketVolume": 870823,
    "averageVolume": 1387276,
    "averageVolume10days": 1103410,
    "averageDailyVolume10Day": 1103410,
    "bid": 460.65,
    "ask": 462.03,
    "bidSize": 1,
    "askSize": 2,
    "marketCap": 124792168448,
    "fiftyTwoWeekLow": 387.03,
    "fiftyTwoWeekHigh": 533.78,
    "allTimeHigh": 533.78,
    "allTimeLow": 2.3125,
    "priceToSalesTrailing12Months": 2.8201618,
    "fiftyDayAverage": 468.0766,
    "twoHundredDayAverage": 483.8847,
    "trailingAnnualDividendRate": 6.33,
    "trailingAnnualDividendYield": 0.013600911,
    "currency": "USD",
    "tradeable": false,
    "enterpriseValue": 185051152384,
    "profitMargins": 0.11767,
    "floatShares": 269813063,
    "sharesOutstanding": 270329392,
    "sharesShort": 4024816,
    "sharesShortPriorMonth": 4308605,
    "sharesShortPreviousMonthDate": 1757894400,
    "dateShortInterest": 1760486400,
    "sharesPercentSharesOut": 0.0149,
    "heldPercentInsiders": 0.00182,
    "heldPercentInstitutions": 0.83522004,
    "shortRatio": 2.79,
    "shortPercentOfFloat": 0.0149,
    "impliedSharesOutstanding": 270329392,
    "bookValue": 93.127,
    "priceToBook": 4.9569945,
    "lastFiscalYearEnd": 1729987200,
    "nextFiscalYearEnd": 1761523200,
    "mostRecentQuarter": 1753574400,
    "earningsQuarterlyGrowth": -0.257,
    "netIncomeToCommon": 5207000064,
    "trailingEps": 19.16,
    "forwardEps": 22.17,
    "lastSplitFactor": "2:1",
    "lastSplitDate": 1196726400,
    "enterpriseToRevenue": 4.182,
    "enterpriseToEbitda": 21.889,
    "52WeekChange": 0.14924812,
    "SandP52WeekChange": 0.19736934,
    "lastDividendValue": 1.62,
    "lastDividendDate": 1759190400,
    "quoteType": "EQUITY",
    "currentPrice": 461.63,
    "targetHighPrice": 724.0,
    "targetLowPrice": 440.0,
    "targetMeanPrice": 524.9491,
    "targetMedianPrice": 513.5,
    "recommendationMean": 2.16667,
    "recommendationKey": "buy",
    "numberOfAnalystOpinions": 22,
    "totalCash": 7225999872,
    "totalCashPerShare": 26.73,
    "ebitda": 8454000128,
    "totalDebt": 67396001792,
    "quickRatio": 2.003,
    "currentRatio": 2.229,
    "totalRevenue": 44250001408,
    "debtToEquity": 266.767,
    "revenuePerShare": 162.983,
    "returnOnAssets": 0.03736,
    "returnOnEquity": 0.21399,
    "grossProfits": 12133999616,
    "freeCashflow": 2331249920,
    "operatingCashflow": 8556000256,
    "earningsGrowth": -0.245,
    "revenueGrowth": -0.086,
    "grossMargins": 0.27421,
    "ebitdaMargins": 0.19105,
    "operatingMargins": 0.15094,
    "financialCurrency": "USD",
    "symbol": "DE",
    "language": "en-US",
    "region": "US",
    "typeDisp": "Equity",
    "quoteSourceName": "Delayed Quote",
    "triggerable": true,
    "customPriceAlertConfidence": "HIGH",
    "exchangeTimezoneName": "America/New_York",
    "exchangeTimezoneShortName": "EST",
    "gmtOffSetMilliseconds": -18000000,
    "esgPopulated": false,
    "corporateActions": [],
    "postMarketTime": 1761954643,
    "regularMarketTime": 1761940802,
    "exchange": "NYQ",
    "messageBoardId": "finmb_266112",
    "market": "us_market",
    "hasPrePostMarketData": true,
    "firstTradeDateMilliseconds": 76253400000,
    "postMarketChangePercent": 0.08014971,
    "postMarketPrice": 462.0,
    "postMarketChange": 0.36999512,
    "regularMarketChange": -3.78,
    "regularMarketDayRange": "458.72 - 464.54",
    "fullExchangeName": "NYSE",
    "averageDailyVolume3Month": 1387276,
    "fiftyTwoWeekLowChange": 74.600006,
    "fiftyTwoWeekLowChangePercent": 0.19274993,
    "fiftyTwoWeekRange": "387.03 - 533.78",
    "fiftyTwoWeekHighChange": -72.150024,
    "fiftyTwoWeekHighChangePercent": -0.13516809,
    "fiftyTwoWeekChangePercent": 14.924812,
    "dividendDate": 1762732800,
    "earningsTimestamp": 1764163800,
    "earningsTimestampStart": 1764163800,
    "earningsTimestampEnd": 1764163800,
    "earningsCallTimestampStart": 1763650800,
    "earningsCallTimestampEnd": 1763650800,
    "isEarningsDateEstimate": false,
    "epsTrailingTwelveMonths": 19.16,
    "epsForward": 22.17,
    "epsCurrentYear": 18.42192,
    "priceEpsCurrentYear": 25.058733,
    "fiftyDayAverageChange": -6.446594,
    "fiftyDayAverageChangePercent": -0.01377252,
    "twoHundredDayAverageChange": -22.2547,
    "twoHundredDayAverageChangePercent": -0.04599174,
    "sourceInterval": 15,
    "exchangeDataDelayedBy": 0,
    "averageAnalystRating": "2.2 - Buy",
    "cryptoTradeable": false,
    "regularMarketChangePercent": -0.812187,
    "regularMarketPrice": 461.63,
    "marketState": "CLOSED",
    "shortName": "Deere & Company",
    "longName": "Deere & Company",
    "trailingPegRatio": 1.5605
}